[
  {
    "title": "1.  \"Homelessness Assistance Application Template\"",
    "summary": "2.  This template is used by individuals to formally apply for homelessness assistance under Part 7 of the Housing Act 1996. It supports the legal argument of the applicant's eligibility and need for housing assistance, detailing personal, household, and immigration information, as well as any support needs or health conditions.",
    "filename": "homelessness.docx"
  },
  {
    "title": "1.  \"Homelessness Application Review Request Template\"",
    "summary": "2.  This template is used to formally request a review of a decision made on a homelessness application under Section 202 of the Housing Act 1996. It supports the legal argument of the applicant disagreeing with the council's decision, providing space to detail the reasons and evidence for the disagreement. It is specifically applicable to individuals who have been unsuccessful in their homelessness application.",
    "filename": "section202_review.docx"
  }
]